[
  {
    "id": 1764540080772,
    "employeeId": "1",
    "date": "2025-11-30",
    "timeIn": "10:38",
    "timeOut": "10:40",
    "status": "on-time"
  },
  {
    "id": 1764540102195,
    "employeeId": "1",
    "date": "2025-11-30",
    "timeIn": "10:38",
    "timeOut": "10:40",
    "status": "on-time"
  },
  {
    "id": 1764540111622,
    "employeeId": "1",
    "date": "2025-11-30",
    "timeIn": "10:38",
    "timeOut": "10:40",
    "status": "on-time"
  },
  {
    "id": 1764540592427,
    "employeeId": "1",
    "date": "2025-11-30",
    "timeIn": "10:38",
    "timeOut": "10:40",
    "status": "on-time"
  }
]